lib_x17_cloudmeta-1.0.0.dist-info/licenses/LICENSE
xcloudmeta/__init__.py
xcloudmeta/base/__init__.py
xcloudmeta/base/file.py
xcloudmeta/base/folder.py
xcloudmeta/base/modulekind.py
xcloudmeta/base/tests/__init__.py
xcloudmeta/base/tests/test_class_file_all.py
xcloudmeta/base/tests/test_class_folder_all.py
xcloudmeta/base/tests/test_class_modulekind_all.py
xcloudmeta/centre/__init__.py
xcloudmeta/centre/centre.py
xcloudmeta/centre/layout.py
xcloudmeta/centre/namespace.py
xcloudmeta/centre/overlay.py
xcloudmeta/centre/tests/test_class_centre_all.py
xcloudmeta/centre/tests/test_class_layout_all.py
xcloudmeta/centre/tests/test_class_namespace_all.py
xcloudmeta/centre/tests/test_class_overlay_all.py
xcloudmeta/component/__init__.py
xcloudmeta/component/makefile.py
xcloudmeta/component/metafile.py
xcloudmeta/component/tests/__init__.py
xcloudmeta/component/tests/test_class_makefile_all.py
xcloudmeta/component/tests/test_class_metafile_all.py
xcloudmeta/module/__init__.py
xcloudmeta/module/environ.py
xcloudmeta/module/module.py
xcloudmeta/module/package.py
xcloudmeta/module/platform.py
xcloudmeta/module/service.py
xcloudmeta/module/tests/test_class_environ_all.py
xcloudmeta/module/tests/test_class_module_all.py
xcloudmeta/module/tests/test_class_package_all.py
xcloudmeta/module/tests/test_class_platform_all.py
xcloudmeta/module/tests/test_class_service_all.py
lib_x17_cloudmeta-1.0.0.dist-info/METADATA
lib_x17_cloudmeta-1.0.0.dist-info/WHEEL
lib_x17_cloudmeta-1.0.0.dist-info/top_level.txt
lib_x17_cloudmeta-1.0.0.dist-info/RECORD
