Metadata-Version: 2.4
Name: lib-x17-cloudmeta
Version: 1.0.0
Summary: cloud centre module for x17 echosystem
Author-email: Xing Xing <x.xing.work@gmail.com>
License: MIT
Requires-Python: >=3.11
License-File: LICENSE
Provides-Extra: dev
Requires-Dist: pytest>=8.0; extra == "dev"
Requires-Dist: pytest-cov>=6.0; extra == "dev"
Requires-Dist: ruff>=0.13; extra == "dev"
Requires-Dist: setuptools; extra == "dev"
Requires-Dist: wheel; extra == "dev"
Requires-Dist: twine; extra == "dev"
Requires-Dist: build; extra == "dev"
Dynamic: license-file
